server/__init__.py
server/server_database.py
server/server_gui.py
server/server_side.py
server/common/__init__.py
server/common/decos.py
server/common/descryptors.py
server/common/errors.py
server/common/metaclasses.py
server/common/utilities.py
server/common/variables.py
server/doc/__init__.py
server/doc/source/__init__.py
server/doc/source/conf.py
server/log/__init__.py
server/log/configs/__init__.py
server/log/configs/client_log_settings.py
server/log/configs/server_log_settings.py
server/server/__init__.py
server/server/add_user.py
server/server/config_window.py
server/server/core.py
server/server/database.py
server/server/main_window.py
server/server/remove_user.py
server/server/server_side.py
server/server/stat_window.py
server/unit_tests/__init__.py
server/unit_tests/test_client_side.py
server/unit_tests/test_server_side.py
server/unit_tests/test_utilities.py
beksilter_messenger_server-0.0.1.dist-info/METADATA
beksilter_messenger_server-0.0.1.dist-info/WHEEL
beksilter_messenger_server-0.0.1.dist-info/top_level.txt
beksilter_messenger_server-0.0.1.dist-info/RECORD
